{
  "project_info": {
    "project_number": "326167600675",
    "project_id": "queen-s-hospital",
    "storage_bucket": "queen-s-hospital.firebasestorage.app"
  },
  "client": [
    {
      "client_info": {
        "mobilesdk_app_id": "1:326167600675:android:6a0848b88826b4e72edb96",
        "android_client_info": {
          "package_name": "com.example.queenshospital2"
        }
      },
      "oauth_client": [],
      "api_key": [
        {
          "current_key": "AIzaSyBp2Ix5cA0rrlqBf3IXCdsumoIe3PwfmPs"
        }
      ],
      "services": {
        "appinvite_service": {
          "other_platform_oauth_client": []
        }
      }
    }
  ],
  "configuration_version": "1"
}